jsonbot/__init__.py
jsonbot/jsonbot.py
jsonbot-1.0.6.dist-info/METADATA
jsonbot-1.0.6.dist-info/WHEEL
jsonbot-1.0.6.dist-info/top_level.txt
jsonbot-1.0.6.dist-info/RECORD
