Metadata-Version: 2.4
Name: jsonbot
Version: 1.0.6
Summary: A simple Json object to Bot library built on top of a osonbot library
Home-page: https://github.com/sinofarmonov323/jsonbot
Author: https://t.me/jackson_rodger
Classifier: Programming Language :: Python :: 3
Classifier: License :: OSI Approved :: MIT License
Classifier: Operating System :: OS Independent
Requires-Python: >=3.10
Requires-Dist: osonbot
Dynamic: author
Dynamic: classifier
Dynamic: description
Dynamic: description-content-type
Dynamic: home-page
Dynamic: requires-dist
Dynamic: requires-python
Dynamic: summary
